Bhaskara/ClassProcessingUnit.py
Bhaskara/CompilerV1.py
Bhaskara/ConditonalProcessingUnit.py
Bhaskara/ExpressionTree.py
Bhaskara/ExpressionTree1.py
Bhaskara/FunctionalProcessingUnit.py
Bhaskara/LPUTest.py
Bhaskara/LoopProcessingUnit.py
Bhaskara/LoopProcessingUnit1.py
Bhaskara/LoopProcessingUnit2.py
Bhaskara/LoopProcessingUnite.py
Bhaskara/Prakamya'sLoopTree.py
Bhaskara/PrakamyasLoopTree.py
Bhaskara/ProcessFunction.py
Bhaskara/ProcessSetElements.py
Bhaskara/TempNestedLoopProcessingUnit.py
Bhaskara/__init__.py
Bhaskara/cmptest.py
Bhaskara/compiler.py
Bhaskara/IOSTREAM/InputOutput.py
Bhaskara/IOSTREAM/SplitString.py
Bhaskara/IOSTREAM/__init__.py
Bhaskara/StringAlgorithm/ConditionSplit.py
Bhaskara/StringAlgorithm/ConditionSplitV2.py
Bhaskara/StringAlgorithm/ConditionSplitV3.py
Bhaskara/StringAlgorithm/ExtractFuncNameParams.py
Bhaskara/StringAlgorithm/SplitString.py
Bhaskara/StringAlgorithm/TokenizeVariableDefinition.py
Bhaskara/StringAlgorithm/__init__.py
Bhaskara/StringAlgorithm/newfile.py
Bhaskara-4.1.6.4.6.dist-info/LICENCE
Bhaskara-4.1.6.4.6.dist-info/METADATA
Bhaskara-4.1.6.4.6.dist-info/WHEEL
Bhaskara-4.1.6.4.6.dist-info/top_level.txt
Bhaskara-4.1.6.4.6.dist-info/RECORD
