Metadata-Version: 2.1
Name: Bhaskara
Version: 4.1.6.4.6
Summary: Bhaskara Programming Engine
Author: Prakamya Khare
Author-email: khareprakamya27@gmail.com
License: MIT
Classifier: Programming Language :: Python :: 3
Classifier: License :: OSI Approved :: MIT License
Classifier: Operating System :: OS Independent
Requires-Python: >=3.6
License-File: LICENCE
